iScanVCFMerge/__init__.py
iScanVCFMerge/iScanVCFMerge.py
iScanVCFMerge-1.1.dist-info/LICENSE
iScanVCFMerge-1.1.dist-info/METADATA
iScanVCFMerge-1.1.dist-info/WHEEL
iScanVCFMerge-1.1.dist-info/entry_points.txt
iScanVCFMerge-1.1.dist-info/top_level.txt
iScanVCFMerge-1.1.dist-info/RECORD
