Metadata-Version: 2.1
Name: iScanVCFMerge
Version: 1.1
Summary: Python tool to merge cross-species Illumina iScan genotype data with a reference set of genotypes from a pre-existing source.
Home-page: https://github.com/baneslab/iScanVCFMerge
Author: Banes, G. L., Meyers, J. and Fountain, E. D.
Author-email: banes@wisc.edu
License: MIT
Project-URL: Bug Tracker, https://github.com/baneslab/iScanVCFMerge/issues
Platform: any
Classifier: License :: OSI Approved :: MIT License
Classifier: Operating System :: OS Independent
Classifier: Programming Language :: Python :: 3.9
Requires-Python: >=3.9
License-File: LICENSE
Requires-Dist: requests
Requires-Dist: python-version (>="3.9")
Requires-Dist: pandas (>="1.3.2")
Requires-Dist: pysam (>="0.16.0.1")
